pyhlml/__init__.py
pyhlml/hlml_error.py
pyhlml/hlml_lib.py
pyhlml/hlml_types.py
pyhlml/main.py
pyhlml-1.9.0.580.1.dist-info/LICENSE
pyhlml-1.9.0.580.1.dist-info/METADATA
pyhlml-1.9.0.580.1.dist-info/WHEEL
pyhlml-1.9.0.580.1.dist-info/top_level.txt
pyhlml-1.9.0.580.1.dist-info/RECORD
